mpl_table/__init__.py
mpl_table/api.py
mpl_table-0.1.6.dist-info/LICENSE
mpl_table-0.1.6.dist-info/WHEEL
mpl_table-0.1.6.dist-info/METADATA
mpl_table-0.1.6.dist-info/RECORD
