Metadata-Version: 2.1
Name: mpl-table
Version: 0.1.6
Summary: Create custom table using matplotlib.
Home-page: https://github.com/geo7/mpl_table
License: MIT
Keywords: matplotlib,table,custom,heatmap
Author: George Lenton
Author-email: georgelenton@gmail.com
Requires-Python: >=3.8,<4.0
Classifier: License :: OSI Approved :: MIT License
Classifier: Programming Language :: Python :: 3
Classifier: Programming Language :: Python :: 3.8
Classifier: Programming Language :: Python :: 3.9
Requires-Dist: matplotlib (>=3.4.3,<4.0.0)
Requires-Dist: pandas (>=1.3.4,<2.0.0)
